limpopo/__init__.py
limpopo/const.py
limpopo/dto.py
limpopo/exceptions.py
limpopo/question.py
limpopo/services/__init__.py
limpopo/services/archetype.py
limpopo/services/telegram.py
limpopo/services/viber.py
limpopo/storages/__init__.py
limpopo/storages/archetype.py
limpopo/storages/fake.py
limpopo/storages/postgres/.gitignore
limpopo/storages/postgres/__init__.py
limpopo/storages/postgres/migrations/README
limpopo/storages/postgres/migrations/env.py
limpopo/storages/postgres/migrations/script.py.mako
limpopo/storages/postgres/migrations/versions/cfae1eb34e12_initial_metadata.py
limpopo/storages/postgres/storage.py
limpopo/storages/postgres/tables.py
limpopo-0.1.2.dist-info/WHEEL
limpopo-0.1.2.dist-info/METADATA
limpopo-0.1.2.dist-info/RECORD
