Metadata-Version: 2.1
Name: limpopo
Version: 0.1.2
Summary: limpopo is a framework that allows you to create an application for conducting surveys via messengers
License: MIT
Author: limpopooooo
Requires-Python: >=3.6.1,<4.0
Classifier: Development Status :: 2 - Pre-Alpha
Classifier: License :: OSI Approved :: MIT License
Classifier: Programming Language :: Python
Classifier: Programming Language :: Python :: 3
Classifier: Programming Language :: Python :: 3.6
Classifier: Programming Language :: Python :: 3.7
Classifier: Programming Language :: Python :: 3.8
Classifier: Programming Language :: Python :: 3.9
Provides-Extra: postgres-migrations
Provides-Extra: postgres-storage
Requires-Dist: Telethon[pillow,cryptg] (>=1.18.2,<2.0.0)
